setup.cfg
setup.py
sdep/__init__.py
sdep/__main__.py
sdep/app.py
sdep/cli.py
sdep/config.py
sdep.egg-info/PKG-INFO
sdep.egg-info/SOURCES.txt
sdep.egg-info/dependency_links.txt
sdep.egg-info/entry_points.txt
sdep.egg-info/requires.txt
sdep.egg-info/top_level.txt