Metadata-Version: 1.1
Name: sdep
Version: 0.1.0
Summary: A cli for easily deploying static websites
Home-page: https://github.com/mattjmcnaughton/sdep
Author: Matt McNaughton
Author-email: mattjmcnaughton@gmail.com
License: MIT
Download-URL: https://github.com/mattjmcnaughton/sdep/tarball/0.1.0
Keywords: deployments,cli
Platform: UNKNOWN
